clearml/__init__.py
clearml/errors.py
clearml/logger.py
clearml/model.py
clearml/py.typed
clearml/task.py
clearml/task_parameters.py
clearml/version.py
clearml/automation/__init__.py
clearml/automation/auto_scaler.py
clearml/automation/aws_driver.py
clearml/automation/cloud_driver.py
clearml/automation/controller.py
clearml/automation/job.py
clearml/automation/monitor.py
clearml/automation/optimization.py
clearml/automation/parameters.py
clearml/automation/scheduler.py
clearml/automation/trigger.py
clearml/automation/hpbandster/__init__.py
clearml/automation/hpbandster/bandster.py
clearml/automation/optuna/__init__.py
clearml/automation/optuna/optuna.py
clearml/backend_api/__init__.py
clearml/backend_api/api_proxy.py
clearml/backend_api/utils.py
clearml/backend_api/config/__init__.py
clearml/backend_api/config/default/api.conf
clearml/backend_api/config/default/logging.conf
clearml/backend_api/schema/__init__.py
clearml/backend_api/schema/action.py
clearml/backend_api/schema/service.py
clearml/backend_api/services/__init__.py
clearml/backend_api/services/v2_13/__init__.py
clearml/backend_api/services/v2_13/auth.py
clearml/backend_api/services/v2_13/events.py
clearml/backend_api/services/v2_13/models.py
clearml/backend_api/services/v2_13/organization.py
clearml/backend_api/services/v2_13/projects.py
clearml/backend_api/services/v2_13/queues.py
clearml/backend_api/services/v2_13/tasks.py
clearml/backend_api/services/v2_13/workers.py
clearml/backend_api/services/v2_20/__init__.py
clearml/backend_api/services/v2_20/auth.py
clearml/backend_api/services/v2_20/events.py
clearml/backend_api/services/v2_20/models.py
clearml/backend_api/services/v2_20/organization.py
clearml/backend_api/services/v2_20/pipelines.py
clearml/backend_api/services/v2_20/projects.py
clearml/backend_api/services/v2_20/queues.py
clearml/backend_api/services/v2_20/tasks.py
clearml/backend_api/services/v2_20/workers.py
clearml/backend_api/services/v2_23/__init__.py
clearml-2.1.3.dist-info/LICENSE
clearml-2.1.3.dist-info/METADATA
clearml-2.1.3.dist-info/WHEEL
clearml-2.1.3.dist-info/entry_points.txt
clearml-2.1.3.dist-info/top_level.txt
clearml-2.1.3.dist-info/RECORD
