Metadata-Version: 2.1
Name: clearml
Version: 2.1.3
Summary: ClearML - Auto-Magical Experiment Manager, Version Control, and MLOps for AI
Home-page: https://github.com/clearml/clearml
Author: ClearML
Author-email: support@clear.ml
License: Apache License 2.0
Keywords: clearml trains development machine deep learning version control machine-learning machinelearning deeplearning deep-learning experiment-manager experimentmanager
Classifier: Development Status :: 5 - Production/Stable
Classifier: Intended Audience :: Developers
Classifier: Intended Audience :: Science/Research
Classifier: Operating System :: POSIX :: Linux
Classifier: Operating System :: MacOS :: MacOS X
Classifier: Operating System :: Microsoft
Classifier: Topic :: Scientific/Engineering :: Artificial Intelligence
Classifier: Topic :: Software Development
Classifier: Topic :: Software Development :: Version Control
Classifier: Topic :: System :: Logging
Classifier: Topic :: System :: Monitoring
Classifier: Programming Language :: Python :: 3.6
Classifier: Programming Language :: Python :: 3.7
Classifier: Programming Language :: Python :: 3.8
Classifier: Programming Language :: Python :: 3.9
Classifier: Programming Language :: Python :: 3.10
Classifier: Programming Language :: Python :: 3.11
Classifier: Programming Language :: Python :: 3.12
Classifier: Programming Language :: Python :: 3.13
Classifier: Programming Language :: Python :: 3.14
Classifier: License :: OSI Approved :: Apache Software License
License-File: LICENSE
Requires-Dist: attrs (>=18.0)
Requires-Dist: furl (>=2.0.0)
Requires-Dist: jsonschema (>=2.6.0)
Requires-Dist: numpy (>=1.10)
Requires-Dist: pathlib2 (>=2.3.0)
Requires-Dist: psutil (>=3.4.2)
Requires-Dist: pyparsing (>=2.0.3)
Requires-Dist: python-dateutil (>=2.6.1)
Requires-Dist: pyjwt (<2.11.0,>=2.4.0)
Requires-Dist: PyYAML (>=3.12)
Requires-Dist: six (>=1.16.0)
Requires-Dist: urllib3 (>=1.21.1)
Requires-Dist: Pillow (>=7.0.0) ; python_version < "3.8"
Requires-Dist: requests (>=2.20.0) ; python_version < "3.8"
Requires-Dist: Pillow (>=10.3.0) ; python_version >= "3.8"
Requires-Dist: referencing (<0.40) ; python_version >= "3.8"
Requires-Dist: requests (>=2.32.0) ; python_version >= "3.8"
Provides-Extra: azure
Requires-Dist: azure-storage-blob (>=12.0.0) ; extra == 'azure'
Provides-Extra: gs
Requires-Dist: google-cloud-storage (>=1.13.2) ; extra == 'gs'
Provides-Extra: router
Requires-Dist: fastapi (>=0.115.2) ; extra == 'router'
Requires-Dist: uvicorn (>=0.31.1) ; extra == 'router'
Requires-Dist: httpx (>=0.27.2) ; extra == 'router'
Provides-Extra: s3
Requires-Dist: boto3 (>=1.9) ; extra == 's3'
